codeslice/__init__.py
codeslice/__main__.py
codeslice/dependency_tracer.py
codeslice/multi_file_tracer.py
codeslice-0.1.1.dist-info/WHEEL
codeslice-0.1.1.dist-info/entry_points.txt
codeslice-0.1.1.dist-info/METADATA
codeslice-0.1.1.dist-info/RECORD
