Metadata-Version: 2.3
Name: codeslice
Version: 0.1.1
Summary: A Python tool for tracing variable dependencies in Python code using AST analysis
Author: Samuel S. Watson
Author-email: Samuel S. Watson <samuel.s.watson@gmail.com>
Requires-Dist: questionary>=2.1.0
Requires-Dist: typer>=0.16.0
Requires-Dist: pyyaml>=6.0
Requires-Dist: pytest>=8.4.1 ; extra == 'dev'
Requires-Dist: ruff>=0.12.7 ; extra == 'dev'
Requires-Python: >=3.12
Provides-Extra: dev
